TFdashboard-2019.6.1.dist-info/DESCRIPTION.rst
TFdashboard-2019.6.1.dist-info/METADATA
TFdashboard-2019.6.1.dist-info/RECORD
TFdashboard-2019.6.1.dist-info/WHEEL
TFdashboard-2019.6.1.dist-info/entry_points.txt
TFdashboard-2019.6.1.dist-info/metadata.json
TFdashboard-2019.6.1.dist-info/top_level.txt
src/__init__.py
src/dashboard.py
src/widgets/TrimTab.py
src/widgets/__init__.py
src/widgets/range.py
